{
  "updated": "2026-05-10T06:40:43.084Z",
  "total": 4,
  "streams": {
    "10.au": {
      "id": "10.au",
      "name": "10",
      "url": "https://youtube.com/watch?v=ePNuDY3nsSs",
      "logo": "https://raw.githubusercontent.com/iptv-org/database/master/logos/10.au.png",
      "group": "news",
      "source": "youtube",
      "status": "live",
      "country": "AU",
      "categories": [
        "news"
      ]
    },
    "100NEWS.ua": {
      "id": "100NEWS.ua",
      "name": "100% NEWS",
      "url": "https://youtube.com/watch?v=S9rPY6pqPDc",
      "logo": "https://raw.githubusercontent.com/iptv-org/database/master/logos/100news.ua.png",
      "group": "news",
      "source": "youtube",
      "status": "live",
      "country": "UA",
      "categories": [
        "news",
        "business"
      ]
    },
    "100NLTV.nl": {
      "id": "100NLTV.nl",
      "name": "100% NL TV",
      "url": "https://youtube.com/watch?v=Fj1LJzHsuhk",
      "logo": "https://raw.githubusercontent.com/iptv-org/database/master/logos/100nltv.nl.png",
      "group": "music",
      "source": "youtube",
      "status": "live",
      "country": "NL",
      "categories": [
        "music"
      ]
    },
    "101tvMalaga.es": {
      "id": "101tvMalaga.es",
      "name": "101tv Malaga",
      "url": "https://youtube.com/watch?v=QEa8VWWtvYQ",
      "logo": "https://raw.githubusercontent.com/iptv-org/database/master/logos/101tvmalaga.es.png",
      "group": "news",
      "source": "youtube",
      "status": "live",
      "country": "ES",
      "categories": [
        "news"
      ]
    }
  }
}